pennylane_ls/MultiQuditDevice.py
pennylane_ls/MultiQuditOps.py
pennylane_ls/SingleQuditDevice.py
pennylane_ls/SingleQuditOps.py
pennylane_ls/__init__.py
pennylane_ls/_version.py
pennylane_ls-0.1.0.dist-info/LICENSE
pennylane_ls-0.1.0.dist-info/METADATA
pennylane_ls-0.1.0.dist-info/WHEEL
pennylane_ls-0.1.0.dist-info/entry_points.txt
pennylane_ls-0.1.0.dist-info/top_level.txt
pennylane_ls-0.1.0.dist-info/RECORD
